clang_format_docs.py
clang_format_docs-0.3.2.dist-info/licenses/LICENSE
clang_format_docs-0.3.2.dist-info/licenses/LICENSE_blacken_docs
clang_format_docs-0.3.2.dist-info/METADATA
clang_format_docs-0.3.2.dist-info/WHEEL
clang_format_docs-0.3.2.dist-info/entry_points.txt
clang_format_docs-0.3.2.dist-info/top_level.txt
clang_format_docs-0.3.2.dist-info/RECORD
